<?xml version="1.0" encoding="utf-8"?>

<DoorList>
  
  <door name="sewerHatch">
    <id>1</id>
    <x>1100</x>
    <y>1050</y>
    <open>0</open>
    <type>0</type>
    <area>1</area>
  </door>

  <door name="LellesQualityMerchandiseDoor">
    <id>2</id>
    <x>535</x>
    <y>350</y>
    <open>1</open>
    <type>2</type>
    <area>2</area>
  </door>
  
  <door name="House1Door">
    <id>3</id>
    <x>685</x>
    <y>350</y>
    <open>1</open>
    <type>2</type>
    <area>3</area>
  </door>

  <door name="House2Door">
    <id>4</id>
    <x>835</x>
    <y>350</y>
    <open>1</open>
    <type>2</type>
    <area>4</area>
  </door>

  <door name="TheDrunkenDragonInn">
    <id>5</id>
    <x>535</x>
    <y>1150</y>
    <open>1</open>
    <type>2</type>
    <area>5</area>
  </door>
  
</DoorList>